hyperleaup/__init__.py
hyperleaup/creation_mode.py
hyperleaup/creator.py
hyperleaup/hyper_config.py
hyperleaup/hyper_file.py
hyperleaup/hyper_utils.py
hyperleaup/publisher.py
hyperleaup/spark_fixture.py
hyperleaup-0.1.2.dist-info/METADATA
hyperleaup-0.1.2.dist-info/WHEEL
hyperleaup-0.1.2.dist-info/licenses/LICENSE
hyperleaup-0.1.2.dist-info/RECORD
