Metadata-Version: 2.1
Name: hyperleaup
Version: 0.1.2
Summary: Create and publish Tableau Hyper files from Apache Spark DataFrames and Spark SQL.
Project-URL: Homepage, https://github.com/goodwillpunning/hyperleaup
Project-URL: Bug Tracker, https://github.com/goodwillpunning/hyperleaup/issues
Author-email: Will Girten <will.girten@databricks.com>
License-File: LICENSE
Keywords: Spark,Tableau,extract,hyper
Classifier: License :: OSI Approved :: Apache Software License
Classifier: Operating System :: OS Independent
Classifier: Programming Language :: Python :: 3
Requires-Python: >=3.6
Requires-Dist: pyspark
Requires-Dist: requests
Requires-Dist: tableauhyperapi
Requires-Dist: tableauserverclient
Requires-Dist: urllib3
